Subway Signal Controller Verilog/subwayseq.v
module subwayseq(clk,reset,p1,p2,out,crntSt,nxtSt);
input clk,reset,p1,p2;
output out,crntSt,nxtSt;

reg[2:0] crntSt;
reg[2:0] nxtSt;
reg out;

localparam s0=3'b000, s
1=3'b001, s2=3'b010, s3=3'b011, s4=3'b100, s5=3'b101;

always@ (posedge clk)

	if(reset)
	
		crntSt<=s0;
		
	else
	    crntSt <= nxtSt; 
	    
	    
always@ (p1 or p2 or crntSt)

	begin
	
		nxtSt <= crntSt;
		
		case(crntSt)
		
			s0:
				begin
				
					if (p1 & !p2)
						begin
							nxtSt<=s1;
							out<=1;
						end
					else if (!p1 & p2)
						begin
							nxtSt<=s5;
							out=0;
						end
					else
						begin
							nxtSt<=s0;
							out=0;
						end
				end
			
			s1:
				begin
				
					if (!p1 & p2)
						begin
							nxtSt<=s2;
							out<=1;
						end
					else if(p1 & !p2)
						begin
							nxtSt<=s0;
							out<=1;
						end
					else
						begin
							nxtSt<=s1;
							out<=1;
						end
				end
			
			s2:
				begin
				
					if (p1 & !p2)
						begin
							nxtSt<=s3;
							out<=1;
						end
					else
						begin
							nxtSt<=s2;
							out=1;
						end
				end
			
			s3:
				begin
				
					if (!p1 & p2)
						begin
							nxtSt<=s4;
							out<=1;
						end
					else if(p1 & !p2)
						begin
							nxtSt<=s2;
							out<=1;
						end
					else
						begin
							nxtSt<=s3;
							out<=1;
						end
				end
			
			s4:
				begin
				
					if (!p1 & p2)
						begin
							nxtSt<=s5;
							out<=1;
						end
					else
						begin
							nxtSt<=s4;
							out<=1;
						end
				end
			s5:
			
				begin
					
					if (p1 & !p2)
						begin
							nxtSt<=s0;
							out<=0;
						end
					else if(!p1 & p2)
						begin
							nxtSt<=s4;
							out<=0;
						end
					else
						begin
							nxtSt<=s5;
							out<=0;
						end
					end
		endcase
	end
endmodule

Subway Signal Controller Verilog/subwayseq.vcd
$comment
Copyright (C) 1991-2010 Altera Corporation
Your use of Altera Corporation's design tools, logic functions 
and other software and tools, and its AMPP partner logic 
functions, and any output files from any of the foregoing 
(including device programming or simulation files), and any 
associated documentation or information are expressly subject 
to the terms and conditions of the Altera Program License 
Subscription Agreement, Altera MegaCore Function License 
Agreement, or other applicable license agreement, including, 
without limitation, that your use is for the sole purpose of 
programming logic devices manufactured by Altera and sold by 
Altera or its authorized distributors.  Please refer to the 
applicable agreement for further details.
$end

$date 
  11/30/2018 15:55:58 
$end
$version 
 QUARTUS_VCD_EXPORT 1.0 
$end
$timescale
  1 ps
$end
$scope module subwayseq $end
$var reg 1 ! reset $end
$var reg 1 " clk $end
$var reg 1 # p1 $end
$var reg 1 $ p2 $end
$var reg 3 % crntSt[2:0] $end
$var reg 1 & out $end
$var reg 1 ' nxtSt[0] $end
$var reg 1 ( nxtSt[1] $end
$var reg 1 ) nxtSt[2] $end
$upscope $end
$enddefinitions $end
#0
$dumpvars
1!
0"
0#
0$
b0 %
0&
0'
0(
0)
$end
#500
1"
#1000
0"
#1500
1"
#2000
0"
#2500
0!
1"
1$
b101 %
1)
#3000
0"
#3500
1"
b100 %
1&
1'
#4000
0"
#4500
1"
b101 %
0&
0'
#5000
0"
1#
0$
0)
#5500
1"
b0 %
1&
1'
#6000
0"
#6500
1"
b1 %
0'
#7000
0"
#7500
1"
1$
1'
#8000
0"
#8500
1"
#9000
0"
#9500
1"
#10000
0"
0#
0$
#10500
1"
#11000
0"
#11500
1"
#12000
0"
#12500
1"
1$
b10 %
0'
1(
#13000
0"
#13500
1"
#14000
0"
#14500
1"
#15000
0"
1#
0$
1'
#15500
1"
b11 %
0'
#16000
0"
#16500
1"
b10 %
1'
#17000
0"
#17500
1"
1$
0'
#18000
0"
#18500
1"
#19000
0"
#19500
1"
#20000
0"
0#
0$
#20500
1"
#21000
0"
#21500
1"
#22000
0"
#22500
1"
1$
#23000
0"
#23500
1"
#24000
0"
#24500
1"
#25000
0"
1#
0$
1'
#25500
1"
b11 %
0'
#26000
0"
#26500
1"
b10 %
1'
#27000
0"
#27500
1"
1$
0'
#28000
0"
#28500
1"
#29000
0"
#29500
1"
#30000
0"
0#
0$
#30500
1"
#31000
0"
#31500
1"
#32000
0"
#32500
1"
1$
#33000
0"
#33500
1"
#34000
0"
#34500
1"
#35000
0"
1#
0$
1'
#35500
1"
b11 %
0'
#36000
0"
#36500
1"
b10 %
1'
#37000
0"
#37500
1"
1$
0'
#38000
0"
#38500
1"
#39000
0"
#39500
1"
#40000
0"
0#
0$
#40500
1"
#41000
0"
#41500
1"
#42000
0"
#42500
1"
1$
#43000
0"
#43500
1"
#44000
0"
#44500
1"
#45000
0"
1#
0$
1'
#45500
1"
b11 %
0'
#46000
0"
#46500
1"
b10 %
1'
#47000
0"
#47500
1"
1$
0'
#48000
0"
#48500
1"
#49000
0"
#49500
1"
#50000
0"
0#
0$
#50500
1"
#51000
0"
#51500
1"
#52000
0"
#52500
1"
1$
#53000
0"
#53500
1"
#54000
0"
#54500
1"
#55000
0"
1#
0$
1'
#55500
1"
b11 %
0'
#56000
0"
#56500
1"
b10 %
1'
#57000
0"
#57500
1"
1$
0'
#58000
0"
#58500
1"
#59000
0"
#59500
1"
#60000
0"
0#
0$
#60500
1"
#61000
0"
#61500
1"
#62000
0"
#62500
1"
1$
#63000
0"
#63500
1"
#64000
0"
#64500
1"
#65000
0"
1#
0$
1'
#65500
1"
b11 %
0'
#66000
0"
#66500
1"
b10 %
1'
#67000
0"
#67500
1"
1$
0'
#68000
0"
#68500
1"
#69000
0"
#69500
1"
#70000
0"
0#
0$
#70500
1"
#71000
0"
#71500
1"
#72000
0"
#72500
1"
1$
#73000
0"
#73500
1"
#74000
0"
#74500
1"
#75000
0"
1#
0$
1'
#75500
1"
b11 %
0'
#76000
0"
#76500
1"
b10 %
1'
#77000
0"
#77500
1"
1$
0'
#78000
0"
#78500
1"
#79000
0"
#79500
1"
#80000
0"
0#
0$
#80500
1"
#81000
0"
#81500
1"
#82000
0"
#82500
1"
1$
#83000
0"
#83500
1"
#84000
0"
#84500
1"
#85000
0"
1#
0$
1'
#85500
1"
b11 %
0'
#86000
0"
#86500
1"
b10 %
1'
#87000
0"
#87500
1"
1$
0'
#88000
0"
#88500
1"
#89000
0"
#89500
1"
#90000
0"
0#
0$
#90500
1"
#91000
0"
#91500
1"
#92000
0"
#92500
1"
1$
#93000
0"
#93500
1"
#94000
0"
#94500
1"
#95000
0"
1#
0$
1'
#95500
1"
b11 %
0'
#96000
0"
#96500
1"
b10 %
1'
#97000
0"
#97500
1"
1$
0'
#98000
0"
#98500
1"
#99000
0"
#99500
1"
#100000
0"
0#
0$
#100500
1"
#101000
0"
#101500
1"
#102000
0"
#102500
1"
1$
#103000
0"
#103500
1"
#104000
0"
#104500
1"
#105000
0"
1#
0$
1'
#105500
1"
b11 %
0'
#106000
0"
#106500
1"
b10 %
1'
#107000
0"
#107500
1"
1$
0'
#108000
0"
#108500
1"
#109000
0"
#109500
1"
#110000
0"
0#
0$
#110500
1"
#111000
0"
#111500
1"
#112000
0"
#112500
1"
1$
#113000
0"
#113500
1"
#114000
0"
#114500
1"
#115000
0"
1#
0$
1'
#115500
1"
b11 %
0'
#116000
0"
#116500
1"
b10 %
1'
#117000
0"
#117500
1"
1$
0'
#118000
0"
#118500
1"
#119000
0"
#119500
1"
#120000
0"
0#
0$
#120500
1"
#121000
0"
#121500
1"
#122000
0"
#122500
1"
1$
#123000
0"
#123500
1"
#124000
0"
#124500
1"
#125000
0"
1#
0$
1'
#125500
1"
b11 %
0'
#126000
0"
#126500
1"
b10 %
1'
#127000
0"
#127500
1"
1$
0'
#128000
0"
#128500
1"
#129000
0"
#129500
1"
#130000
0"
0#
0$
#130500
1"
#131000
0"
#131500
1"
#132000
0"
#132500
1"
1$
#133000
0"
#133500
1"
#134000
0"
#134500
1"
#135000
0"
1#
0$
1'
#135500
1"
b11 %
0'
#136000
0"
#136500
1"
b10 %
1'
#137000
0"
#137500
1"
1$
0'
#138000
0"
#138500
1"
#139000
0"
#139500
1"
#140000
0"
0#
0$
#140500
1"
#141000
0"
#141500
1"
#142000
0"
#142500
1"
1$
#143000
0"
#143500
1"
#144000
0"
#144500
1"
#145000
0"
1#
0$
1'
#145500
1"
b11 %
0'
#146000
0"
#146500
1"
b10 %
1'
#147000
0"
#147500
1"
1$
0'
#148000
0"
#148500
1"
#149000
0"
#149500
1"
#150000
0"
0#
0$
#150500
1"
#151000
0"
#151500
1"
#152000
0"
#152500
1"
1$
#153000
0"
#153500
1"
#154000
0"
#154500
1"
#155000
0"
1#
0$
1'
#155500
1"
b11 %
0'
#156000
0"
#156500
1"
b10 %
1'
#157000
0"
#157500
1"
1$
0'
#158000
0"
#158500
1"
#159000
0"
#159500
1"
#160000
0"
0#
0$
#160500
1"
#161000
0"
#161500
1"
#162000
0"
#162500
1"
1$
#163000
0"
#163500
1"
#164000
0"
#164500
1"
#165000
0"
1#
0$
1'
#165500
1"
b11 %
0'
#166000
0"
#166500
1"
b10 %
1'
#167000
0"
#167500
1"
1$
0'
#168000
0"
#168500
1"
#169000
0"
#169500
1"
#170000
0"
0#
0$
#170500
1"
#171000
0"
#171500
1"
#172000
0"
#172500
1"
1$
#173000
0"
#173500
1"
#174000
0"
#174500
1"
#175000
0"
1#
0$
1'
#175500
1"
b11 %
0'
#176000
0"
#176500
1"
b10 %
1'
#177000
0"
#177500
1"
1$
0'
#178000
0"
#178500
1"
#179000
0"
#179500
1"
#180000
0"
0#
0$
#180500
1"
#181000
0"
#181500
1"
#182000
0"
#182500
1"
1$
#183000
0"
#183500
1"
#184000
0"
#184500
1"
#185000
0"
1#
0$
1'
#185500
1"
b11 %
0'
#186000
0"
#186500
1"
b10 %
1'
#187000
0"
#187500
1"
1$
0'
#188000
0"
#188500
1"
#189000
0"
#189500
1"
#190000
0"
0#
0$
#190500
1"
#191000
0"
#191500
1"
#192000
0"
#192500
1"
1$
#193000
0"
#193500
1"
#194000
0"
#194500
1"
#195000
0"
1#
0$
1'
#195500
1"
b11 %
0'
#196000
0"
#196500
1"
b10 %
1'
#197000
0"
#197500
1"
1$
0'
#198000
0"
#198500
1"
#199000
0"
#199500
1"
#200000
0"
0#
0$
#200500
1"
#201000
0"
#201500
1"
#202000
0"
#202500
1"
1$
#203000
0"
#203500
1"
#204000
0"
#204500
1"
#205000
0"
1#
0$
1'
#205500
1"
b11 %
0'
#206000
0"
#206500
1"
b10 %
1'
#207000
0"
#207500
1"
1$
0'
#208000
0"
#208500
1"
#209000
0"
#209500
1"
#210000
0"
0#
0$
#210500
1"
#211000
0"
#211500
1"
#212000
0"
#212500
1"
1$
#213000
0"
#213500
1"
#214000
0"
#214500
1"
#215000
0"
1#
0$
1'
#215500
1"
b11 %
0'
#216000
0"
#216500
1"
b10 %
1'
#217000
0"
#217500
1"
1$
0'
#218000
0"
#218500
1"
#219000
0"
#219500
1"
#220000
0"
0#
0$
#220500
1"
#221000
0"
#221500
1"
#222000
0"
#222500
1"
1$
#223000
0"
#223500
1"
#224000
0"
#224500
1"
#225000
0"
1#
0$
1'
#225500
1"
b11 %
0'
#226000
0"
#226500
1"
b10 %
1'
#227000
0"
#227500
1"
1$
0'
#228000
0"
#228500
1"
#229000
0"
#229500
1"
#230000
0"
0#
0$
#230500
1"
#231000
0"
#231500
1"
#232000
0"
#232500
1"
1$
#233000
0"
#233500
1"
#234000
0"
#234500
1"
#235000
0"
1#
0$
1'
#235500
1"
b11 %
0'
#236000
0"
#236500
1"
b10 %
1'
#237000
0"
#237500
1"
1$
0'
#238000
0"
#238500
1"
#239000
0"
#239500
1"
#240000
0"
0#
0$
#240500
1"
#241000
0"
#241500
1"
#242000
0"
#242500
1"
1$
#243000
0"
#243500
1"
#244000
0"
#244500
1"
#245000
0"
1#
0$
1'
#245500
1"
b11 %
0'
#246000
0"
#246500
1"
b10 %
1'
#247000
0"
#247500
1"
1$
0'
#248000
0"
#248500
1"
#249000
0"
#249500
1"
#250000
0"
0#
0$
#250500
1"
#251000
0"
#251500
1"
#252000
0"
#252500
1"
1$
#253000
0"
#253500
1"
#254000
0"
#254500
1"
#255000
0"
1#
0$
1'
#255500
1"
b11 %
0'
#256000
0"
#256500
1"
b10 %
1'
#257000
0"
#257500
1"
1$
0'
#258000
0"
#258500
1"
#259000
0"
#259500
1"
#260000
0"
0#
0$
#260500
1"
#261000
0"
#261500
1"
#262000
0"
#262500
1"
1$
#263000
0"
#263500
1"
#264000
0"
#264500
1"
#265000
0"
1#
0$
1'
#265500
1"
b11 %
0'
#266000
0"
#266500
1"
b10 %
1'
#267000
0"
#267500
1"
1$
0'
#268000
0"
#268500
1"
#269000
0"
#269500
1"
#270000
0"
0#
0$
#270500
1"
#271000
0"
#271500
1"
#272000
0"
#272500
1"
1$
#273000
0"
#273500
1"
#274000
0"
#274500
1"
#275000
1!
0"
1#
0$
1'
#275500
1"
b0 %
0(
#276000
0"
#276500
1"
#277000
0"
#277500
0!
1"
1$
0&
0'
#278000
0"
#278500
1"
#279000
0"
#279500
1"
#280000
1!
0"
0#
0$
#280500
1"
#281000
0"
#281500
1"
#282000
0"
#282500
0!
1"
1$
b101 %
1)
#283000
0"
#283500
1"
b100 %
1&
1'
#284000
0"
#284500
1"
b101 %
0&
0'
#285000
1!
0"
1#
0$
0)
#285500
1"
b0 %
1&
1'
#286000
0"
#286500
1"
#287000
0"
#287500
0!
1"
1$
0&
0'
#288000
0"
#288500
1"
#289000
0"
#289500
1"
#290000
1!
0"
0#
0$
#290500
1"
#291000
0"
#291500
1"
#292000
0"
#292500
0!
1"
1$
b101 %
1)
#293000
0"
#293500
1"
b100 %
1&
1'
#294000
0"
#294500
1"
b101 %
0&
0'
#295000
1!
0"
1#
0$
0)
#295500
1"
b0 %
1&
1'
#296000
0"
#296500
1"
#297000
0"
#297500
0!
1"
1$
0&
0'
#298000
0"
#298500
1"
#299000
0"
#299500
1"
#300000
1!
0"
0#
0$
#300500
1"
#301000
0"
#301500
1"
#302000
0"
#302500
0!
1"
1$
b101 %
1)
#303000
0"
#303500
1"
b100 %
1&
1'
#304000
0"
#304500
1"
b101 %
0&
0'
#305000
1!
0"
1#
0$
0)
#305500
1"
b0 %
1&
1'
#306000
0"
#306500
1"
#307000
0"
#307500
0!
1"
1$
0&
0'
#308000
0"
#308500
1"
#309000
0"
#309500
1"
#310000
1!
0"
0#
0$
#310500
1"
#311000
0"
#311500
1"
#312000
0"
#312500
0!
1"
1$
b101 %
1)
#313000
0"
#313500
1"
b100 %
1&
1'
#314000
0"
#314500
1"
b101 %
0&
0'
#315000
1!
0"
1#
0$
0)
#315500
1"
b0 %
1&
1'
#316000
0"
#316500
1"
#317000
0"
#317500
0!
1"
1$
0&
0'
#318000
0"
#318500
1"
#319000
0"
#319500
1"
#320000
1!
0"
0#
0$
#320500
1"
#321000
0"
#321500
1"
#322000
0"
#322500
0!
1"
1$
b101 %
1)
#323000
0"
#323500
1"
b100 %
1&
1'
#324000
0"
#324500
1"
b101 %
0&
0'
#325000
1!
0"
1#
0$
0)
#325500
1"
b0 %
1&
1'
#326000
0"
#326500
1"
#327000
0"
#327500
0!
1"
1$
0&
0'
#328000
0"
#328500
1"
#329000
0"
#329500
1"
#330000
1!
0"
0#
0$
#330500
1"
#331000
0"
#331500
1"
#332000
0"
#332500
0!
1"
1$
b101 %
1)
#333000
0"
#333500
1"
b100 %
1&
1'
#334000
0"
#334500
1"
b101 %
0&
0'
#335000
1!
0"
1#
0$
0)
#335500
1"
b0 %
1&
1'
#336000
0"
#336500
1"
#337000
0"
#337500
0!
1"
1$
0&
0'
#338000
0"
#338500
1"
#339000
0"
#339500
1"
#340000
1!
0"
0#
0$
#340500
1"
#341000
0"
#341500
1"
#342000
0"
#342500
0!
1"
1$
b101 %
1)
#343000
0"
#343500
1"
b100 %
1&
1'
#344000
0"
#344500
1"
b101 %
0&
0'
#345000
1!
0"
1#
0$
0)
#345500
1"
b0 %
1&
1'
#346000
0"
#346500
1"
#347000
0"
#347500
0!
1"
1$
0&
0'
#348000
0"
#348500
1"
#349000
0"
#349500
1"
#350000
1!
0"
0#
0$
#350500
1"
#351000
0"
#351500
1"
#352000
0"
#352500
0!
1"
1$
b101 %
1)
#353000
0"
#353500
1"
b100 %
1&
1'
#354000
0"
#354500
1"
b101 %
0&
0'
#355000
1!
0"
1#
0$
0)
#355500
1"
b0 %
1&
1'
#356000
0"
#356500
1"
#357000
0"
#357500
0!
1"
1$
0&
0'
#358000
0"
#358500
1"
#359000
0"
#359500
1"
#360000
1!
0"
0#
0$
#360500
1"
#361000
0"
#361500
1"
#362000
0"
#362500
0!
1"
1$
b101 %
1)
#363000
0"
#363500
1"
b100 %
1&
1'
#364000
0"
#364500
1"
b101 %
0&
0'
#365000
1!
0"
1#
0$
0)
#365500
1"
b0 %
1&
1'
#366000
0"
#366500
1"
#367000
0"
#367500
0!
1"
1$
0&
0'
#368000
0"
#368500
1"
#369000
0"
#369500
1"
#370000
1!
0"
0#
0$
#370500
1"
#371000
0"
#371500
1"
#372000
0"
#372500
0!
1"
1$
b101 %
1)
#373000
0"
#373500
1"
b100 %
1&
1'
#374000
0"
#374500
1"
b101 %
0&
0'
#375000
1!
0"
1#
0$
0)
#375500
1"
b0 %
1&
1'
#376000
0"
#376500
1"
#377000
0"
#377500
0!
1"
1$
0&
0'
#378000
0"
#378500
1"
#379000
0"
#379500
1"
#380000
1!
0"
0#
0$
#380500
1"
#381000
0"
#381500
1"
#382000
0"
#382500
0!
1"
1$
b101 %
1)
#383000
0"
#383500
1"
b100 %
1&
1'
#384000
0"
#384500
1"
b101 %
0&
0'
#385000
1!
0"
1#
0$
0)
#385500
1"
b0 %
1&
1'
#386000
0"
#386500
1"
#387000
0"
#387500
0!
1"
1$
0&
0'
#388000
0"
#388500
1"
#389000
0"
#389500
1"
#390000
1!
0"
0#
0$
#390500
1"
#391000
0"
#391500
1"
#392000
0"
#392500
0!
1"
1$
b101 %
1)
#393000
0"
#393500
1"
b100 %
1&
1'
#394000
0"
#394500
1"
b101 %
0&
0'
#395000
1!
0"
1#
0$
0)
#395500
1"
b0 %
1&
1'
#396000
0"
#396500
1"
#397000
0"
#397500
0!
1"
1$
0&
0'
#398000
0"
#398500
1"
#399000
0"
#399500
1"
#400000
1!
0"
0#
0$
#400500
1"
#401000
0"
#401500
1"
#402000
0"
#402500
0!
1"
1$
b101 %
1)
#403000
0"
#403500
1"
b100 %
1&
1'
#404000
0"
#404500
1"
b101 %
0&
0'
#405000
1!
0"
1#
0$
0)
#405500
1"
b0 %
1&
1'
#406000
0"
#406500
1"
#407000
0"
#407500
0!
1"
1$
0&
0'
#408000
0"
#408500
1"
#409000
0"
#409500
1"
#410000
1!
0"
0#
0$
#410500
1"
#411000
0"
#411500
1"
#412000
0"
#412500
0!
1"
1$
b101 %
1)
#413000
0"
#413500
1"
b100 %
1&
1'
#414000
0"
#414500
1"
b101 %
0&
0'
#415000
1!
0"
1#
0$
0)
#415500
1"
b0 %
1&
1'
#416000
0"
#416500
1"
#417000
0"
#417500
0!
1"
1$
0&
0'
#418000
0"
#418500
1"
#419000
0"
#419500
1"
#420000
1!
0"
0#
0$
#420500
1"
#421000
0"
#421500
1"
#422000
0"
#422500
0!
1"
1$
b101 %
1)
#423000
0"
#423500
1"
b100 %
1&
1'
#424000
0"
#424500
1"
b101 %
0&
0'
#425000
1!
0"
1#
0$
0)
#425500
1"
b0 %
1&
1'
#426000
0"
#426500
1"
#427000
0"
#427500
0!
1"
1$
0&
0'
#428000
0"
#428500
1"
#429000
0"
#429500
1"
#430000
1!
0"
0#
0$
#430500
1"
#431000
0"
#431500
1"
#432000
0"
#432500
0!
1"
1$
b101 %
1)
#433000
0"
#433500
1"
b100 %
1&
1'
#434000
0"
#434500
1"
b101 %
0&
0'
#435000
1!
0"
1#
0$
0)
#435500
1"
b0 %
1&
1'
#436000
0"
#436500
1"
#437000
0"
#437500
0!
1"
1$
0&
0'
#438000
0"
#438500
1"
#439000
0"
#439500
1"
#440000
1!
0"
0#
0$
#440500
1"
#441000
0"
#441500
1"
#442000
0"
#442500
0!
1"
1$
b101 %
1)
#443000
0"
#443500
1"
b100 %
1&
1'
#444000
0"
#444500
1"
b101 %
0&
0'
#445000
1!
0"
1#
0$
0)
#445500
1"
b0 %
1&
1'
#446000
0"
#446500
1"
#447000
0"
#447500
0!
1"
1$
0&
0'
#448000
0"
#448500
1"
#449000
0"
#449500
1"
#450000
1!
0"
0#
0$
#450500
1"
#451000
0"
#451500
1"
#452000
0"
#452500
0!
1"
1$
b101 %
1)
#453000
0"
#453500
1"
b100 %
1&
1'
#454000
0"
#454500
1"
b101 %
0&
0'
#455000
1!
0"
1#
0$
0)
#455500
1"
b0 %
1&
1'
#456000
0"
#456500
1"
#457000
0"
#457500
0!
1"
1$
0&
0'
#458000
0"
#458500
1"
#459000
0"
#459500
1"
#460000
1!
0"
0#
0$
#460500
1"
#461000
0"
#461500
1"
#462000
0"
#462500
0!
1"
1$
b101 %
1)
#463000
0"
#463500
1"
b100 %
1&
1'
#464000
0"
#464500
1"
b101 %
0&
0'
#465000
1!
0"
1#
0$
0)
#465500
1"
b0 %
1&
1'
#466000
0"
#466500
1"
#467000
0"
#467500
0!
1"
1$
0&
0'
#468000
0"
#468500
1"
#469000
0"
#469500
1"
#470000
1!
0"
0#
0$
#470500
1"
#471000
0"
#471500
1"
#472000
0"
#472500
0!
1"
1$
b101 %
1)
#473000
0"
#473500
1"
b100 %
1&
1'
#474000
0"
#474500
1"
b101 %
0&
0'
#475000
1!
0"
1#
0$
0)
#475500
1"
b0 %
1&
1'
#476000
0"
#476500
1"
#477000
0"
#477500
0!
1"
1$
0&
0'
#478000
0"
#478500
1"
#479000
0"
#479500
1"
#480000
1!
0"
0#
0$
#480500
1"
#481000
0"
#481500
1"
#482000
0"
#482500
0!
1"
1$
b101 %
1)
#483000
0"
#483500
1"
b100 %
1&
1'
#484000
0"
#484500
1"
b101 %
0&
0'
#485000
1!
0"
1#
0$
0)
#485500
1"
b0 %
1&
1'
#486000
0"
#486500
1"
#487000
0"
#487500
0!
1"
1$
0&
0'
#488000
0"
#488500
1"
#489000
0"
#489500
1"
#490000
1!
0"
0#
0$
#490500
1"
#491000
0"
#491500
1"
#492000
0"
#492500
0!
1"
1$
b101 %
1)
#493000
0"
#493500
1"
b100 %
1&
1'
#494000
0"
#494500
1"
b101 %
0&
0'
#495000
1!
0"
1#
0$
0)
#495500
1"
b0 %
1&
1'
#496000
0"
#496500
1"
#497000
0"
#497500
0!
1"
1$
0&
0'
#498000
0"
#498500
1"
#499000
0"
#499500
1"
#500000
1!
0"
0#
0$
#500500
1"
#501000
0"
#501500
1"
#502000
0"
#502500
0!
1"
1$
b101 %
1)
#503000
0"
#503500
1"
b100 %
1&
1'
#504000
0"
#504500
1"
b101 %
0&
0'
#505000
1!
0"
1#
0$
0)
#505500
1"
b0 %
1&
1'
#506000
0"
#506500
1"
#507000
0"
#507500
0!
1"
1$
0&
0'
#508000
0"
#508500
1"
#509000
0"
#509500
1"
#510000
1!
0"
0#
0$
#510500
1"
#511000
0"
#511500
1"
#512000
0"
#512500
0!
1"
1$
b101 %
1)
#513000
0"
#513500
1"
b100 %
1&
1'
#514000
0"
#514500
1"
b101 %
0&
0'
#515000
1!
0"
1#
0$
0)
#515500
1"
b0 %
1&
1'
#516000
0"
#516500
1"
#517000
0"
#517500
0!
1"
1$
0&
0'
#518000
0"
#518500
1"
#519000
0"
#519500
1"
#520000
1!
0"
0#
0$
#520500
1"
#521000
0"
#521500
1"
#522000
0"
#522500
0!
1"
1$
b101 %
1)
#523000
0"
#523500
1"
b100 %
1&
1'
#524000
0"
#524500
1"
b101 %
0&
0'
#525000
1!
0"
1#
0$
0)
#525500
1"
b0 %
1&
1'
#526000
0"
#526500
1"
#527000
0"
#527500
0!
1"
1$
0&
0'
#528000
0"
#528500
1"
#529000
0"
#529500
1"
#530000
1!
0"
0#
0$
#530500
1"
#531000
0"
#531500
1"
#532000
0"
#532500
0!
1"
1$
b101 %
1)
#533000
0"
#533500
1"
b100 %
1&
1'
#534000
0"
#534500
1"
b101 %
0&
0'
#535000
1!
0"
1#
0$
0)
#535500
1"
b0 %
1&
1'
#536000
0"
#536500
1"
#537000
0"
#537500
0!
1"
1$
0&
0'
#538000
0"
#538500
1"
#539000
0"
#539500
1"
#540000
1!
0"
0#
0$
#540500
1"
#541000
0"
#541500
1"
#542000
0"
#542500
0!
1"
1$
b101 %
1)
#543000
0"
#543500
1"
b100 %
1&
1'
#544000
0"
#544500
1"
b101 %
0&
0'
#545000
1!
0"
1#
0$
0)
#545500
1"
b0 %
1&
1'
#546000
0"
#546500
1"
#547000
0"
#547500
0!
1"
1$
0&
0'
#548000
0"
#548500
1"
#549000
0"
#549500
1"
#550000
1!
0"
0#
0$
#550500
1"
#551000
0"
#551500
1"
#552000
0"
#552500
0!
1"
1$
b101 %
1)
#553000
0"
#553500
1"
b100 %
1&
1'
#554000
0"
#554500
1"
b101 %
0&
0'
#555000
1!
0"
1#
0$
0)
#555500
1"
b0 %
1&
1'
#556000
0"
#556500
1"
#557000
0"
#557500
0!
1"
1$
0&
0'
#558000
0"
#558500
1"
#559000
0"
#559500
1"
#560000
1!
0"
0#
0$
#560500
1"
#561000
0"
#561500
1"
#562000
0"
#562500
0!
1"
1$
b101 %
1)
#563000
0"
#563500
1"
b100 %
1&
1'
#564000
0"
#564500
1"
b101 %
0&
0'
#565000
1!
0"
1#
0$
0)
#565500
1"
b0 %
1&
1'
#566000
0"
#566500
1"
#567000
0"
#567500
0!
1"
1$
0&
0'
#568000
0"
#568500
1"
#569000
0"
#569500
1"
#570000
1!
0"
0#
0$
#570500
1"
#571000
0"
#571500
1"
#572000
0"
#572500
0!
1"
1$
b101 %
1)
#573000
0"
#573500
1"
b100 %
1&
1'
#574000
0"
#574500
1"
b101 %
0&
0'
#575000
1!
0"
1#
0$
0)
#575500
1"
b0 %
1&
1'
#576000
0"
#576500
1"
#577000
0"
#577500
0!
1"
1$
0&
0'
#578000
0"
#578500
1"
#579000
0"
#579500
1"
#580000
1!
0"
0#
0$
#580500
1"
#581000
0"
#581500
1"
#582000
0"
#582500
0!
1"
1$
b101 %
1)
#583000
0"
#583500
1"
b100 %
1&
1'
#584000
0"
#584500
1"
b101 %
0&
0'
#585000
1!
0"
1#
0$
0)
#585500
1"
b0 %
1&
1'
#586000
0"
#586500
1"
#587000
0"
#587500
0!
1"
1$
0&
0'
#588000
0"
#588500
1"
#589000
0"
#589500
1"
#590000
1!
0"
0#
0$
#590500
1"
#591000
0"
#591500
1"
#592000
0"
#592500
0!
1"
1$
b101 %
1)
#593000
0"
#593500
1"
b100 %
1&
1'
#594000
0"
#594500
1"
b101 %
0&
0'
#595000
1!
0"
1#
0$
0)
#595500
1"
b0 %
1&
1'
#596000
0"
#596500
1"
#597000
0"
#597500
0!
1"
1$
0&
0'
#598000
0"
#598500
1"
#599000
0"
#599500
1"
#600000
1!
0"
0#
0$
#600500
1"
#601000
0"
#601500
1"
#602000
0"
#602500
0!
1"
1$
b101 %
1)
#603000
0"
#603500
1"
b100 %
1&
1'
#604000
0"
#604500
1"
b101 %
0&
0'
#605000
1!
0"
1#
0$
0)
#605500
1"
b0 %
1&
1'
#606000
0"
#606500
1"
#607000
0"
#607500
0!
1"
1$
0&
0'
#608000
0"
#608500
1"
#609000
0"
#609500
1"
#610000
1!
0"
0#
0$
#610500
1"
#611000
0"
#611500
1"
#612000
0"
#612500
0!
1"
1$
b101 %
1)
#613000
0"
#613500
1"
b100 %
1&
1'
#614000
0"
#614500
1"
b101 %
0&
0'
#615000
1!
0"
1#
0$
0)
#615500
1"
b0 %
1&
1'
#616000
0"
#616500
1"
#617000
0"
#617500
0!
1"
1$
0&
0'
#618000
0"
#618500
1"
#619000
0"
#619500
1"
#620000
1!
0"
0#
0$
#620500
1"
#621000
0"
#621500
1"
#622000
0"
#622500
0!
1"
1$
b101 %
1)
#623000
0"
#623500
1"
b100 %
1&
1'
#624000
0"
#624500
1"
b101 %
0&
0'
#625000
1!
0"
1#
0$
0)
#625500
1"
b0 %
1&
1'
#626000
0"
#626500
1"
#627000
0"
#627500
0!
1"
1$
0&
0'
#628000
0"
#628500
1"
#629000
0"
#629500
1"
#630000
1!
0"
0#
0$
#630500
1"
#631000
0"
#631500
1"
#632000
0"
#632500
0!
1"
1$
b101 %
1)
#633000
0"
#633500
1"
b100 %
1&
1'
#634000
0"
#634500
1"
b101 %
0&
0'
#635000
1!
0"
1#
0$
0)
#635500
1"
b0 %
1&
1'
#636000
0"
#636500
1"
#637000
0"
#637500
0!
1"
1$
0&
0'
#638000
0"
#638500
1"
#639000
0"
#639500
1"
#640000
1!
0"
0#
0$
#640500
1"
#641000
0"
#641500
1"
#642000
0"
#642500
0!
1"
1$
b101 %
1)
#643000
0"
#643500
1"
b100 %
1&
1'
#644000
0"
#644500
1"
b101 %
0&
0'
#645000
1!
0"
1#
0$
0)
#645500
1"
b0 %
1&
1'
#646000
0"
#646500
1"
#647000
0"
#647500
0!
1"
1$
0&
0'
#648000
0"
#648500
1"
#649000
0"
#649500
1"
#650000
1!
0"
0#
0$
#650500
1"
#651000
0"
#651500
1"
#652000
0"
#652500
0!
1"
1$
b101 %
1)
#653000
0"
#653500
1"
b100 %
1&
1'
#654000
0"
#654500
1"
b101 %
0&
0'
#655000
1!
0"
1#
0$
0)
#655500
1"
b0 %
1&
1'
#656000
0"
#656500
1"
#657000
0"
#657500
0!
1"
1$
0&
0'
#658000
0"
#658500
1"
#659000
0"
#659500
1"
#660000
1!
0"
0#
0$
#660500
1"
#661000
0"
#661500
1"
#662000
0"
#662500
0!
1"
1$
b101 %
1)
